<?xml version="1.0" encoding="UTF-8"?>
<objects serializationModel="Studio.02.02.00">
	<object class="AudioFile" id="{f197bee3-edad-4315-a03d-74ea52498e26}">
		<property name="assetPath">
			<value>BaitShop.wav</value>
		</property>
		<property name="frequencyInKHz">
			<value>44.0999985</value>
		</property>
		<property name="channelCount">
			<value>2</value>
		</property>
		<property name="length">
			<value>1.2074376417233561</value>
		</property>
		<relationship name="masterAssetFolder">
			<destination>{8947bfd8-85a4-4658-892e-65752c94929b}</destination>
		</relationship>
	</object>
</objects>
